LangGPTEval/__init__.py
LangGPTEval/evaluation.py
LangGPTEval/factories.py
LangGPTEval/models.py
LangGPTEval/prompts.py
LangRAGEval-0.1.1.dist-info/LICENSE
LangRAGEval-0.1.1.dist-info/METADATA
LangRAGEval-0.1.1.dist-info/WHEEL
LangRAGEval-0.1.1.dist-info/entry_points.txt
LangRAGEval-0.1.1.dist-info/top_level.txt
LangRAGEval-0.1.1.dist-info/RECORD
