Metadata-Version: 2.1
Name: LangRAGEval
Version: 0.1.1
Summary: LangRAGEval is a library for evaluating responses based on faithfulness, context recall, answer relevancy, and context relevancy.
Home-page: https://github.com/Vprashant/LangGPTEval
Author: Prashant Verma
Author-email: prashant27050@gmail.com
License-File: LICENSE
Requires-Dist: sacrebleu
Requires-Dist: rouge-score
Requires-Dist: bert-score
Requires-Dist: langchain
Requires-Dist: pydantic
